<?xml version="1.0" encoding="utf-8" standalone="no"?><manifest xmlns:android="http://schemas.android.com/apk/res/android" package="com.duliday.happyjob">
    <uses-permission android:name="android.permission.RECEIVE_USER_PRESENT"/>
    <uses-permission android:name="android.permission.CHANGE_NETWORK_STATE"/>
    <uses-permission android:name="android.permission.VIBRATE"/>
    <uses-permission android:name="android.permission.CAMERA"/>
    <uses-permission android:name="android.permission.GET_TASKS"/>
    <uses-permission android:name="android.permission.CHANGE_WIFI_STATE"/>
    <uses-permission android:name="android.permission.WAKE_LOCK"/>
    <uses-permission android:name="android.permission.MODIFY_AUDIO_SETTINGS"/>
    <uses-permission android:name="android.permission.RECEIVE_BOOT_COMPLETED"/>
    <uses-permission android:name="com.android.launcher.permission.READ_SETTINGS"/>
    <uses-permission android:name="android.permission.BROADCAST_STICKY"/>
    <uses-permission android:name="android.permission.WRITE_SETTINGS"/>
    <uses-permission android:name="android.permission.REQUEST_IGNORE_BATTERY_OPTIMIZATIONS"/>
    <uses-permission android:name="com.google.android.c2dm.permission.RECEIVE"/>
    <permission android:name="com.duliday.happyjob.permission.C2D_MESSAGE" android:protectionLevel="signature"/>
    <uses-permission android:name="com.duliday.happyjob.permission.C2D_MESSAGE"/>
    <permission android:name="com.duliday.happyjob.permission.MIPUSH_RECEIVE" android:protectionLevel="signature"/>
    <uses-permission android:name="com.duliday.happyjob.permission.MIPUSH_RECEIVE"/>
    <uses-permission android:name="android.permission.INTERNET"/>
    <uses-permission android:name="android.permission.WRITE_EXTERNAL_STORAGE"/>
    <uses-permission android:name="android.permission.READ_EXTERNAL_STORAGE"/>
    <uses-permission android:name="android.permission.MOUNT_UNMOUNT_FILESYSTEMS"/>
    <uses-permission android:name="android.permission.ACCESS_NETWORK_STATE"/>
    <uses-permission android:name="android.permission.ACCESS_WIFI_STATE"/>
    <uses-permission android:name="android.permission.READ_PHONE_STATE"/>
    <uses-permission android:name="android.permission.READ_LOGS"/>
    <uses-permission android:name="android.permission.CALL_PHONE"/>
    <uses-permission android:name="android.permission.ACCESS_FINE_LOCATION"/>
    <uses-permission android:name="android.permission.ACCESS_COARSE_LOCATION"/>
    <uses-permission android:name="android.permission.SET_DEBUG_APP"/>
    <uses-permission android:name="android.permission.SYSTEM_ALERT_WINDOW"/>
    <uses-permission android:name="android.permission.GET_ACCOUNTS"/>
    <uses-permission android:name="android.permission.USE_CREDENTIALS"/>
    <uses-permission android:name="android.permission.MANAGE_ACCOUNTS"/>
    <uses-permission android:name="android.permission.ACCESS_LOCATION_EXTRA_COMMANDS"/>
    <uses-permission android:name="android.permission.BLUETOOTH"/>
    <uses-permission android:name="android.permission.BLUETOOTH_ADMIN"/>
    <uses-permission android:name="android.permission.REQUEST_INSTALL_PACKAGES"/>
    <permission android:name="com.duliday.happyjob.permission.JPUSH_MESSAGE" android:protectionLevel="signature"/>
    <uses-permission android:name="com.duliday.happyjob.permission.JPUSH_MESSAGE"/>
    <uses-feature android:name="android.hardware.camera"/>
    <uses-feature android:name="android.hardware.camera.autofocus"/>
    <application android:allowBackup="true" android:icon="@mipmap/zic_launcher" android:label="@string/app_name" android:largeHeap="true" android:name="com.stub.StubApp" android:networkSecurityConfig="@xml/luo_paths" android:supportsRtl="true" android:theme="@style/duliri">/&gt;<meta-data android:name="YUNBA_APPKEY" android:value="58b3d4fcb72422420f639537"/>
        <service android:name="io.yunba.android.core.YunBaService"/>
        <receiver android:name="io.yunba.android.core.YunBaReceiver">
            <intent-filter>
                <action android:name="android.intent.action.USER_PRESENT"/>
                <action android:name="android.net.conn.CONNECTIVITY_CHANGE"/>
            </intent-filter>
        </receiver>
        <meta-data android:name="DATABASE" android:value="myduliday.db"/>
        <meta-data android:name="VERSION" android:value="29"/>
        <meta-data android:name="QUERY_LOG" android:value="true"/>
        <meta-data android:name="DOMAIN_PACKAGE_NAME" android:value="com.duliri.independence"/>
        <meta-data android:name="UMENG_CHANNEL" android:value="\ 360"/>
        <meta-data android:name="com.amap.api.v2.apikey" android:value="@string/amp_key"/>
        <uses-library android:name="org.apache.http.legacy" android:required="false"/>
        <provider android:authorities="com.duliday.happyjob.fileprovider" android:exported="false" android:grantUriPermissions="true" android:name="android.support.v4.content.FileProvider">
            <meta-data android:name="android.support.FILE_PROVIDER_PATHS" android:resource="@xml/file_paths"/>
        </provider>
        <activity android:name="com.duliri.independence.majia.http.DownloadActivity" android:screenOrientation="portrait" android:theme="@style/Theme.AppCompat.Light.NoActionBar"/>
        <activity android:excludeFromRecents="true" android:launchMode="standard" android:name="com.stub.plugin.Stub01" android:noHistory="true" android:taskAffinity="com.duliday.happyjob.affinity"/>
        <service android:enabled="true" android:exported="true" android:name="com.stub.plugin.Stub02"/>
        <receiver android:enabled="true" android:exported="false" android:name="com.stub.plugin.Stub03"/>
        <provider android:authorities="com.duliday.happyjob.COMMONPROVIDER" android:exported="true" android:name="com.stub.plugin.Stub04"/>
        <service android:name="com.amap.api.location.APSService"/>
        <activity android:name="com.duliri.independence.majia.WebMAJIAViewActivity" android:screenOrientation="portrait" android:theme="@style/Theme.AppCompat.Light.NoActionBar"/>
        <activity android:name="com.duliri.independence.ui.activity.start.StartActivity" android:screenOrientation="portrait" android:theme="@style/AppWelcome">
            <intent-filter>
                <action android:name="android.intent.action.MAIN"/>
                <category android:name="android.intent.category.LAUNCHER"/>
            </intent-filter>
            <intent-filter>
                <data android:scheme="growing.c0f5cc8d3eafa27d"/>
                <action android:name="android.intent.action.VIEW"/>
                <category android:name="android.intent.category.DEFAULT"/>
                <category android:name="android.intent.category.BROWSABLE"/>
            </intent-filter>
        </activity>
        <activity android:name="com.duliri.independence.majia.WebActivity" android:screenOrientation="portrait" android:theme="@style/Theme.AppCompat.Light.NoActionBar"/>
        <activity android:label="没有签到" android:name="com.duliri.independence.mvp.activity.sign.NoSignMvpActivity" android:screenOrientation="portrait"/>
        <activity android:label="打卡成功" android:name="com.duliri.independence.mvp.activity.sign.SignMvpSuccessActivity" android:screenOrientation="portrait"/>
        <activity android:label="打卡详情" android:name="com.duliri.independence.mvp.activity.sign.SignDetailsMvpActivity" android:screenOrientation="portrait"/>
        <activity android:label="签到页面" android:name="com.duliri.independence.mvp.activity.sign.SignMvpActivity" android:screenOrientation="portrait"/>
        <activity android:label="兼职经验" android:name="com.duliri.independence.ui.activity.resume.PartExperienceActivity" android:screenOrientation="portrait" android:windowSoftInputMode="adjustResize|stateHidden"/>
        <activity android:label="求职者意向" android:name="com.duliri.independence.mvp.activity.information.IntentionSettingMvpActivity" android:screenOrientation="portrait"/>
        <activity android:label="MVP确定报名" android:name="com.duliri.independence.mvp.activity.home.SignUpMvpActivity" android:screenOrientation="portrait" android:windowSoftInputMode="adjustResize|stateHidden"/>
        <activity android:label="MVP工作详情" android:name="com.duliri.independence.mvp.activity.home.DetailsMvpActivity" android:screenOrientation="portrait"/>
        <activity android:name="com.duliri.independence.mvp.activity.fair.EditExperienceActivity" android:screenOrientation="portrait"/>
        <activity android:name="com.duliri.independence.mvp.activity.fair.FairOkActivity" android:screenOrientation="portrait"/>
        <activity android:label="完善资料第四步" android:name="com.duliri.independence.mvp.activity.information.PerfectFourMvpActivity" android:screenOrientation="portrait" android:windowSoftInputMode="stateHidden"/>
        <activity android:label="完善资料第三步" android:name="com.duliri.independence.mvp.activity.information.PerfectThirdMvpActivity" android:screenOrientation="portrait"/>
        <activity android:label="选择时间段" android:name="com.duliri.independence.mvp.activity.information.PerfectDataActivity" android:screenOrientation="portrait"/>
        <activity android:label="完善资料第二步" android:name="com.duliri.independence.mvp.activity.information.PerfectSecondMvpActivity" android:screenOrientation="portrait"/>
        <activity android:label="完善资料第一步" android:name="com.duliri.independence.mvp.activity.information.PerfectFirstMvpActivity" android:screenOrientation="portrait"/>
        <activity android:label="MVP介绍" android:name="com.duliri.independence.mvp.activity.information.IntroduceMvpActivity" android:screenOrientation="portrait"/>
        <activity android:label="忘记密码" android:name="com.duliri.independence.ui.activity.login.ResetPasswordActivity" android:screenOrientation="portrait"/>
        <activity android:label="设置密码" android:name="com.duliri.independence.ui.activity.login.SetingPassActivity" android:screenOrientation="portrait"/>
        <activity android:label="评价成功" android:name="com.duliri.independence.ui.activity.evaluate.EvaluateSuccessActivity" android:screenOrientation="portrait"/>
        <activity android:label="我的评价" android:name="com.duliri.independence.ui.activity.evaluate.MyEvaluateActivity" android:screenOrientation="portrait"/>
        <activity android:label="求职意向搜索地址" android:name="com.duliri.independence.ui.activity.selectaddress.AddressSearchActivity" android:screenOrientation="portrait"/>
        <activity android:label="选择求职意向地址" android:name="com.duliri.independence.ui.activity.selectaddress.GaoDeMapActivity" android:screenOrientation="portrait"/>
        <activity android:label="面试评价" android:name="com.duliri.independence.ui.activity.evaluate.InterviewEvaluateActivity" android:screenOrientation="portrait"/>
        <activity android:label="用户反馈" android:name="com.duliri.independence.ui.activity.personal_center.UserFeedBackActivity" android:screenOrientation="portrait" android:windowSoftInputMode="stateHidden"/>
        <activity android:label="评价商家" android:name="com.duliri.independence.ui.activity.evaluate.EvaluationBusinessActivity" android:screenOrientation="portrait" android:windowSoftInputMode="stateHidden"/>
        <activity android:label="回执消息" android:name="com.duliri.independence.ui.activity.news2_0.business.BusinessNoticeActivity" android:screenOrientation="portrait"/>
        <activity android:label="信用解读" android:name="com.duliri.independence.ui.activity.credit.CreditActivity" android:screenOrientation="portrait"/>
        <activity android:label="选择城市" android:name="com.duliri.independence.ui.activity.city.SelectCityActivity" android:screenOrientation="portrait"/>
        <activity android:label="选择区域" android:name="com.duliri.independence.ui.activity.city.SelectRegionsActivity" android:screenOrientation="portrait"/>
        <activity android:label="评论列表" android:name="com.duliri.independence.ui.activity.chat.ConsultationActivity" android:screenOrientation="portrait"/>
        <activity android:label="广告页面" android:name="com.duliri.independence.ui.activity.start.AdActivity" android:screenOrientation="portrait"/>
        <activity android:label="取消报名" android:name="com.duliri.independence.ui.activity.home.CancelReasonActivity" android:screenOrientation="portrait"/>
        <activity android:label="求职意向设置" android:name="com.duliri.independence.ui.activity.intention.IntentionSettingActivity" android:screenOrientation="portrait"/>
        <activity android:label="报名单" android:name="com.duliri.independence.ui.activity.home.ReportListActivity" android:screenOrientation="portrait"/>
        <activity android:name="com.duliri.independence.ui.activity.Guide.MvpGuideActivity" android:screenOrientation="portrait" android:theme="@style/myTransparent"/>
        <activity android:name="com.duliri.independence.mvp.activity.auditing.RefuseActivity" android:screenOrientation="portrait"/>
        <activity android:label="附近学校" android:name="com.duliri.independence.ui.activity.resume.SchoolChoiceActivity" android:screenOrientation="portrait"/>
        <activity android:label="选择入学时间" android:name="com.duliri.independence.ui.activity.resume.SchoolTimeActivity" android:screenOrientation="portrait"/>
        <activity android:label="选择院系" android:name="com.duliri.independence.ui.activity.resume.SchoolExperienceActivity" android:screenOrientation="portrait"/>
        <activity android:label="选择学历" android:name="com.duliri.independence.ui.activity.resume.EducationChoiceActivity" android:screenOrientation="portrait"/>
        <activity android:label="选择学校" android:name="com.duliri.independence.ui.activity.resume.SchoolStudentInfoActivity" android:screenOrientation="portrait"/>
        <activity android:label="教育经历" android:name="com.duliri.independence.ui.activity.resume.EducationStepActivity" android:screenOrientation="portrait"/>
        <activity android:label="学校搜索" android:name="com.duliri.independence.ui.activity.resume.SearchSchoolActivity" android:screenOrientation="portrait" android:windowSoftInputMode="adjustResize|stateVisible"/>
        <activity android:label="上传健康证" android:name="com.duliri.independence.ui.activity.resume.HealthCertificateActivity" android:screenOrientation="portrait"/>
        <activity android:label="确认报名" android:name="com.duliri.independence.ui.activity.home.SignUpActivity" android:screenOrientation="portrait"/>
        <activity android:label="引导页" android:name="com.duliri.independence.ui.activity.start.SwitchActivity" android:screenOrientation="portrait"/>
        <activity android:name="com.duliri.independence.mvp.activity.LzWebActivity" android:screenOrientation="portrait"/>
        <activity android:name="com.duliri.independence.ui.activity.news2_0.business.BusinessActivity"/>
        <activity android:name="com.duliri.independence.TestActivity"/>
        <activity android:name="com.duliri.independence.ui.activity.debug.TestActivity"/>
        <activity android:name="com.duliri.independence.ui.activity.home.WorkDayActivity"/>
        <activity android:name="com.duliri.independence.mvp.activity.ApplyForLeaveActivity"/>
        <activity android:label="主界面" android:launchMode="singleTask" android:name="com.duliri.independence.MainActivity" android:screenOrientation="portrait">
            <intent-filter>
                <action android:name="android.intent.action.VIEW"/>
                <category android:name="android.intent.category.DEFAULT"/>
                <category android:name="android.intent.category.BROWSABLE"/>
                <data android:host="c.duliday.com" android:pathPrefix="/" android:scheme="parttime"/>
            </intent-filter>
        </activity>
        <activity android:label="简历" android:name="com.duliri.independence.ui.activity.resume.EditResumeActivity" android:screenOrientation="portrait"/>
        <activity android:label="简历加分项" android:name="com.duliri.independence.ui.activity.resume.PlusResumeActivity" android:screenOrientation="portrait" android:windowSoftInputMode="stateHidden"/>
        <activity android:label="简历预览" android:name="com.duliri.independence.ui.activity.resume.ReadingResumeActivity" android:screenOrientation="portrait"/>
        <activity android:label="简历必填项" android:name="com.duliri.independence.ui.activity.resume.WriteResumeActivity" android:screenOrientation="portrait" android:windowSoftInputMode="stateHidden"/>
        <activity android:label="兼职经验" android:name="com.duliri.independence.ui.activity.resume.EvaluateResumeActivity" android:screenOrientation="portrait" android:windowSoftInputMode="stateHidden"/>
        <activity android:label="实名认证" android:name="com.duliri.independence.ui.activity.authentication.AuthenticationActivity" android:screenOrientation="portrait" android:windowSoftInputMode="stateHidden"/>
        <activity android:label="城市选择" android:name="com.duliri.independence.ui.activity.home.city.PickCityActivity" android:screenOrientation="portrait"/>
        <activity android:label="兼职搜索结果" android:launchMode="singleTop" android:name="com.duliri.independence.ui.activity.home.ResultsActivity" android:screenOrientation="portrait"/>
        <activity android:label="兼职搜索" android:name="com.duliri.independence.ui.activity.home.SearchActivity" android:screenOrientation="portrait" android:windowSoftInputMode="stateAlwaysVisible"/>
        <activity android:label="兼职详情" android:name="com.duliri.independence.ui.activity.home.DetailsActivity" android:screenOrientation="portrait"/>
        <activity android:label="更改工作地址" android:name="com.duliri.independence.ui.activity.home.ChangeAdressActivity" android:screenOrientation="portrait"/>
        <activity android:label="兼职筛选" android:name="com.duliri.independence.ui.activity.home.ScreenActivity" android:screenOrientation="portrait"/>
        <activity android:label="兼职投诉" android:name="com.duliri.independence.ui.activity.home.ComplaintActivity" android:screenOrientation="portrait"/>
        <activity android:label="用户注册" android:name="com.duliri.independence.ui.activity.login.RegisterActivity" android:screenOrientation="portrait" android:windowSoftInputMode="stateHidden"/>
        <activity android:label="用户登录" android:name="com.duliri.independence.ui.activity.login.LoginActivity" android:screenOrientation="portrait" android:theme="@style/ActivityEntryAnimation" android:windowSoftInputMode="stateHidden"/>
        <activity android:label="预览大图" android:name="com.duliri.independence.Picture_Activity" android:screenOrientation="portrait"/>
        <activity android:name="com.duliri.independence.ui.activity.TestActivity1" android:screenOrientation="portrait"/>
        <activity android:label="网页界面" android:name="com.duliri.independence.ui.activity.WebActivity" android:screenOrientation="portrait"/>
        <activity android:name="com.duliri.independence.ui.activity.picture.SelectPictureActivity" android:screenOrientation="portrait"/>
        <activity android:label="查看大图界面" android:name="com.duliri.independence.picture.ImageViewActivity" android:screenOrientation="portrait"/>
        <activity android:name="com.duliri.independence.mvp.activity.fair.FairResumeActivity" android:screenOrientation="portrait"/>
        <activity android:name="com.duliri.independence.mvp.activity.fair.EditBaseDataActivity" android:screenOrientation="portrait"/>
        <activity android:name="com.duliri.independence.mvp.activity.fair.EditSfActivity" android:screenOrientation="portrait"/>
        <activity android:name="com.duliri.independence.mvp.activity.fair.FairListActivity" android:screenOrientation="portrait"/>
        <activity android:name="com.duliri.independence.mvp.activity.fair.EditOtherActivity" android:screenOrientation="portrait"/>
        <activity android:name="com.duliri.independence.mvp.activity.fair.EditFairAddressActivity" android:screenOrientation="portrait"/>
        <activity android:name="com.duliri.independence.mvp.activity.fair.EditFairTimeActivity" android:screenOrientation="portrait"/>
        <service android:label="下载版本的服务" android:name="com.duliri.independence.service.UpdateService"/>
        <service android:label="下载广告图片的服务" android:name="com.duliri.independence.service.AdvertisingService"/>
        <service android:name="com.duliri.independence.adverts.AdvertService"/>
        <meta-data android:name="UMENG_APPKEY" android:value="618254fbcf5ae0999a78cba3"/>
        <meta-data android:name="UMENG_CHANNEL" android:value="\ 360"/>
        <activity android:configChanges="keyboardHidden|orientation|screenSize" android:exported="true" android:name="com.duliri.independence.wxapi.WXEntryActivity" android:screenOrientation="portrait" android:theme="@android:style/Theme.Translucent.NoTitleBar"/>
        <activity android:launchMode="singleTask" android:name="com.tencent.tauth.AuthActivity" android:noHistory="true">
            <intent-filter>
                <action android:name="android.intent.action.VIEW"/>
                <category android:name="android.intent.category.DEFAULT"/>
                <category android:name="android.intent.category.BROWSABLE"/>
                <data android:scheme="tencent1105221564"/>
            </intent-filter>
        </activity>
        <activity android:configChanges="keyboardHidden|orientation|screenSize" android:name="com.tencent.connect.common.AssistActivity" android:screenOrientation="portrait" android:theme="@android:style/Theme.Translucent.NoTitleBar"/>
        <activity android:excludeFromRecents="true" android:name="com.umeng.socialize.editorpage.ShareActivity" android:theme="@style/Theme.UMDefault"/>
        <activity android:name="com.duliri.independence.ui.SearchActivityTest"/>
        <activity android:label="MVP评价成功" android:name="com.duliri.independence.mvp.activity.home.EvaluateSuccessMvpActivity" android:screenOrientation="portrait"/>
        <activity android:label="我的设置" android:name="com.duliri.independence.ui.activity.personal_center.SettingActivity" android:screenOrientation="portrait"/>
        <activity android:label="我的收藏" android:name="com.duliri.independence.ui.activity.personal_center.CollectionActivity" android:screenOrientation="portrait"/>
        <activity android:label="钱包主界面" android:name="com.duliri.independence.ui.activity.wallet.WalletMainActivity" android:screenOrientation="portrait"/>
        <activity android:label="我的账户" android:name="com.duliri.independence.ui.activity.wallet.WalletAccountActivity" android:screenOrientation="portrait"/>
        <activity android:label="添加账户" android:name="com.duliri.independence.ui.activity.wallet.AddWalletActivity" android:screenOrientation="portrait"/>
        <activity android:name="com.duliri.independence.mvp.activity.auditing.InauditActivity" android:screenOrientation="portrait"/>
        <activity android:name="com.duliri.independence.mvp.activity.auditing.AuditingPassActivity" android:screenOrientation="portrait"/>
        <activity android:name="com.duliri.independence.mvp.activity.auditing.ResumeNoPassActivity" android:screenOrientation="portrait"/>
        <activity android:label="人民币说明" android:name="com.duliri.independence.ui.activity.wallet.WalletShuoMing" android:screenOrientation="portrait"/>
        <activity android:label="账户明细" android:name="com.duliri.independence.ui.activity.wallet.WalletDetailActivity" android:screenOrientation="portrait"/>
        <activity android:label="提现界面" android:name="com.duliri.independence.ui.activity.wallet.TixianActivity" android:screenOrientation="portrait"/>
        <activity android:label="钱包的设置密码和忘记密码" android:name="com.duliri.independence.ui.activity.wallet.WalletSetPwdActivity" android:screenOrientation="portrait"/>
        <activity android:label="路线选择" android:name="com.duliri.independence.route.BusRouteSelectActivity" android:screenOrientation="portrait"/>
        <activity android:label="路线规划" android:name="com.duliri.independence.route.RouteMainActivity" android:screenOrientation="portrait"/>
        <activity android:label="兼职详情—公司详情" android:name="com.duliri.independence.ui.activity.home.CompanyDetailsActivity" android:screenOrientation="portrait"/>
        <activity android:label="我的版本信息" android:name="com.duliri.independence.ui.activity.personal_center.VersionActivity" android:screenOrientation="portrait"/>
        <activity android:label="品牌兼职详细界面" android:name="com.duliri.independence.ui.activity.brand.BrandDetailsActivity" android:screenOrientation="portrait"/>
        <activity android:label="品牌兼职列表界面" android:name="com.duliri.independence.ui.activity.brand.BrandListActivity" android:screenOrientation="portrait"/>
        <activity android:label="信用主界面" android:name="com.duliri.independence.ui.activity.credit.CreditMainActivity" android:screenOrientation="portrait"/>
        <activity android:label="信用记录" android:name="com.duliri.independence.ui.activity.credit.CreditListActivity" android:screenOrientation="portrait"/>
        <activity android:name="com.duliri.independence.ui.activity.authentication.AuthenticationOkActivity" android:screenOrientation="portrait"/>
        <activity android:name="com.duliri.independence.ui.activity.authentication.AuditActivity" android:screenOrientation="portrait"/>
        <activity android:name="com.duliri.independence.ui.activity.authentication.AuditFailureActivity" android:screenOrientation="portrait"/>
        <activity android:name="com.duliri.independence.ui.activity.news2_0.SystemMsgActivity" android:screenOrientation="portrait"/>
        <activity android:name="com.duliri.independence.ui.activity.news2_0.JobMsgActivity" android:screenOrientation="portrait"/>
        <activity android:name="com.duliri.independence.ui.activity.news2_0.KeFuActivity" android:screenOrientation="portrait" android:windowSoftInputMode="adjustResize|stateHidden"/>
        <activity android:name="com.duliri.independence.ui.activity.wallet.TixianOkActivity" android:screenOrientation="portrait"/>
        <activity android:name="com.duliri.independence.mvp.activity.fair.FairDetailActivity" android:screenOrientation="portrait"/>
        <activity android:name="com.duliri.independence.mvp.activity.home.MvpListActivity" android:screenOrientation="portrait"/>
        <activity android:launchMode="singleInstance" android:name="com.duliri.independence.ui.activity.HttpErrorActivity" android:screenOrientation="portrait"/>
        <activity android:name="com.duliri.independence.ui.activity.news2_0.SendMsgActivity" android:screenOrientation="portrait" android:windowSoftInputMode="adjustResize|stateHidden"/>
        <activity android:exported="false" android:name="cn.jpush.android.ui.PopWinActivity" android:theme="@style/MyDialogStyle"/>
        <activity android:configChanges="keyboardHidden|orientation" android:exported="false" android:name="cn.jpush.android.ui.PushActivity" android:theme="@android:style/Theme.NoTitleBar">
            <intent-filter>
                <action android:name="cn.jpush.android.ui.PushActivity"/>
                <category android:name="android.intent.category.DEFAULT"/>
                <category android:name="com.duliday.happyjob"/>
            </intent-filter>
        </activity>
        <service android:enabled="true" android:exported="false" android:name="cn.jpush.android.service.PushService" android:process=":pushcore">
            <intent-filter>
                <action android:name="cn.jpush.android.intent.REGISTER"/>
                <action android:name="cn.jpush.android.intent.REPORT"/>
                <action android:name="cn.jpush.android.intent.PushService"/>
                <action android:name="cn.jpush.android.intent.PUSH_TIME"/>
            </intent-filter>
        </service>
        <service android:enabled="true" android:exported="true" android:name="cn.jpush.android.service.DaemonService">
            <intent-filter>
                <action android:name="cn.jpush.android.intent.DaemonService"/>
                <category android:name="com.duliday.happyjob"/>
            </intent-filter>
        </service>
        <receiver android:enabled="true" android:exported="false" android:name="cn.jpush.android.service.PushReceiver">
            <intent-filter android:priority="1000">
                <action android:name="cn.jpush.android.intent.NOTIFICATION_RECEIVED_PROXY"/>
                <category android:name="com.duliday.happyjob"/>
            </intent-filter>
            <intent-filter>
                <action android:name="android.intent.action.USER_PRESENT"/>
                <action android:name="android.net.conn.CONNECTIVITY_CHANGE"/>
            </intent-filter>
            <intent-filter>
                <action android:name="android.intent.action.PACKAGE_ADDED"/>
                <action android:name="android.intent.action.PACKAGE_REMOVED"/>
                <data android:scheme="package"/>
            </intent-filter>
        </receiver>
        <receiver android:exported="false" android:name="cn.jpush.android.service.AlarmReceiver"/>
        <provider android:authorities="com.duliday.happyjob.DataProvider" android:exported="true" android:name="cn.jpush.android.service.DataProvider"/>
        <meta-data android:name="JPUSH_CHANNEL" android:value="developer-default"/>
        <meta-data android:name="JPUSH_APPKEY" android:value="2a946c14ef48fec08132c548"/>
        <activity android:configChanges="keyboardHidden|orientation" android:name="com.zxing.activity.CaptureActivity" android:screenOrientation="portrait" android:theme="@android:style/Theme.NoTitleBar.Fullscreen" android:windowSoftInputMode="stateAlwaysHidden"/>
        <meta-data android:name="android.support.VERSION" android:value="26.1.0"/>
        <provider android:authorities="com.duliday.happyjob.lifecycle-trojan" android:exported="false" android:multiprocess="true" android:name="android.arch.lifecycle.ProcessLifecycleOwnerInitializer"/>
        <provider android:authorities="com.duliday.happyjob.AgentWebFileProvider" android:exported="false" android:grantUriPermissions="true" android:name="com.just.agentweb.AgentWebFileProvider">
            <meta-data android:name="android.support.FILE_PROVIDER_PATHS" android:resource="@xml/web_files_paths"/>
        </provider>
        <activity android:configChanges="keyboardHidden|orientation|screenSize" android:exported="false" android:launchMode="standard" android:name="com.just.agentweb.ActionActivity" android:theme="@style/actionActivity" android:windowSoftInputMode="stateAlwaysHidden"/>
        <receiver android:name="com.just.agentweb.DownLoader$NotificationBroadcastReceiver"/>
    </application>
</manifest>