<?xml version="1.0" encoding="utf-8" standalone="no"?><manifest xmlns:android="http://schemas.android.com/apk/res/android" android:compileSdkVersion="28" android:compileSdkVersionCodename="9" android:installLocation="auto" package="com.lenskart.app" platformBuildVersionCode="28" platformBuildVersionName="9">
    <uses-permission android:name="android.permission.INTERNET"/>
    <uses-permission android:name="android.permission.WAKE_LOCK"/>
    <uses-permission android:name="android.permission.VIBRATE"/>
    <uses-permission android:name="android.permission.GET_TASKS"/>
    <uses-permission android:name="android.permission.ACCESS_WIFI_STATE"/>
    <uses-permission android:name="android.permission.WRITE_EXTERNAL_STORAGE"/>
    <uses-permission android:name="android.permission.READ_EXTERNAL_STORAGE"/>
    <uses-permission android:name="android.permission.GET_ACCOUNTS"/>
    <uses-permission android:name="android.permission.USE_CREDENTIALS"/>
    <uses-permission android:name="android.permission.READ_PHONE_STATE"/>
    <uses-permission android:name="android.permission.ACCESS_COARSE_LOCATION"/>
    <uses-permission android:name="android.permission.ACCESS_FINE_LOCATION"/>
    <uses-permission android:name="android.permission.RECEIVE_BOOT_COMPLETED"/>
    <uses-permission android:name="android.permission.SET_ANIMATION_SCALE"/>
    <uses-permission android:name="android.permission.READ_CONTACTS"/>
    <uses-feature android:name="android.hardware.camera"/>
    <uses-permission android:name="com.google.android.c2dm.permission.RECEIVE"/>
    <uses-permission android:name="com.lenskart.app.permission.C2D_MESSAGE"/>
    <permission android:name="com.lenskart.app.permission.C2D_MESSAGE" android:protectionLevel="signature"/>
    <uses-permission android:name="android.permission.CAMERA"/>
    <uses-permission android:name="android.permission.ACCESS_NETWORK_STATE"/>
    <uses-feature android:name="android.hardware.camera.autofocus" android:required="false"/>
    <uses-permission android:name="com.google.android.providers.gsf.permission.READ_GSERVICES"/>
    <uses-feature android:glEsVersion="0x00020000" android:required="true"/>
    <uses-permission android:name="com.google.android.finsky.permission.BIND_GET_INSTALL_REFERRER_SERVICE"/>
    <uses-permission android:name="android.permission.FOREGROUND_SERVICE"/>
    <application android:allowBackup="true" android:appComponentFactory="androidx.core.app.CoreComponentFactory" android:backupAgent="com.lenskart.app.utils.AppBackUpAgent" android:fullBackupContent="@xml/backup_rules" android:fullBackupOnly="true" android:hardwareAccelerated="true" android:icon="@mipmap/ic_launcher" android:label="@string/app_name" android:name="com.lenskart.app.LenskartApplication" android:supportsRtl="true" android:theme="@style/Theme.Lenskart" android:usesCleartextTraffic="true">
        <uses-library android:name="org.apache.http.legacy" android:required="false"/>
        <meta-data android:name="invitereferrals_bid" android:value="@integer/invitereferrals_bid"/>
        <meta-data android:name="invitereferrals_bid_e" android:value="@string/invitereferrals_bid_e"/>
        <meta-data android:name="com.google.firebase.messaging.default_notification_icon" android:resource="@drawable/ic_star_rate_white_18"/>
        <meta-data android:name="com.google.firebase.messaging.default_notification_color" android:resource="@color/background_primary"/>
        <meta-data android:name="CLEVERTAP_NOTIFICATION_ICON" android:value="ic_stat_portrait"/>
        <activity android:name="com.lenskart.app.ui.onboarding.SplashActivity" android:screenOrientation="portrait" android:theme="@style/Theme.Lenskart.SplashScreenTheme" android:windowSoftInputMode="adjustNothing">
            <intent-filter>
                <action android:name="android.intent.action.MAIN"/>
                <category android:name="android.intent.category.LAUNCHER"/>
            </intent-filter>
            <intent-filter>
                <action android:name="action_navigate"/>
                <category android:name="android.intent.category.DEFAULT"/>
                <data android:host="@string/deep_link_host" android:path="@string/action_view_splash" android:scheme="@string/action_view_scheme"/>
            </intent-filter>
            <intent-filter>
                <action android:name="android.intent.action.VIEW"/>
                <category android:name="android.intent.category.DEFAULT"/>
                <category android:name="android.intent.category.BROWSABLE"/>
                <data android:scheme="@string/deep_link_scheme_app"/>
            </intent-filter>
            <intent-filter android:autoVerify="true">
                <action android:name="android.intent.action.VIEW"/>
                <category android:name="android.intent.category.DEFAULT"/>
                <category android:name="android.intent.category.BROWSABLE"/>
                <data android:host="@string/deep_link_host" android:scheme="@string/deep_link_scheme_http"/>
                <data android:host="@string/deep_link_host" android:scheme="@string/deep_link_scheme_https"/>
            </intent-filter>
            <intent-filter android:autoVerify="true" android:label="@string/app_name">
                <action android:name="android.intent.action.VIEW"/>
                <category android:name="android.intent.category.DEFAULT"/>
                <category android:name="android.intent.category.BROWSABLE"/>
                <data android:host="@string/deep_link_host_one_link" android:scheme="@string/deep_link_scheme_http"/>
                <data android:host="@string/deep_link_host_one_link" android:scheme="@string/deep_link_scheme_https"/>
            </intent-filter>
            <intent-filter>
                <action android:name="com.google.android.gms.actions.SEARCH_ACTION"/>
                <category android:name="android.intent.category.DEFAULT"/>
            </intent-filter>
        </activity>
        <activity android:name="com.lenskart.baselayer.ui.DeepLinkHandlerActivity" android:screenOrientation="portrait" android:theme="@style/Theme.Lenskart.NoActionBar"/>
        <activity android:label="@string/title_home" android:name="com.lenskart.app.ui.home.HomeActivity2" android:screenOrientation="portrait" android:theme="@style/Theme.Lenskart.ExtendedToolbar" android:windowSoftInputMode="adjustResize">
            <intent-filter>
                <action android:name="action_navigate"/>
                <category android:name="android.intent.category.DEFAULT"/>
                <data android:host="@string/deep_link_host" android:path="@string/action_view_home" android:scheme="@string/action_view_scheme"/>
            </intent-filter>
        </activity>
        <activity android:label="@string/title_collection" android:name="com.lenskart.app.ui.home.CollectionActivity" android:screenOrientation="portrait" android:theme="@style/Theme.Lenskart" android:windowSoftInputMode="adjustResize">
            <intent-filter>
                <action android:name="action_navigate"/>
                <category android:name="android.intent.category.DEFAULT"/>
                <data android:host="@string/deep_link_host" android:path="@string/action_view_collection" android:scheme="@string/action_view_scheme"/>
            </intent-filter>
        </activity>
        <activity android:label="@string/title_sign_up" android:name="com.lenskart.app.ui.account.UpdateAccountActivity" android:noHistory="false" android:screenOrientation="portrait">
            <intent-filter android:autoVerify="true" android:label="@string/app_name">
                <action android:name="android.intent.action.VIEW"/>
                <category android:name="android.intent.category.DEFAULT"/>
                <category android:name="android.intent.category.BROWSABLE"/>
                <data android:host="@string/deep_link_host_invite_referral" android:scheme="@string/deep_link_host_invite_referral"/>
            </intent-filter>
        </activity>
        <activity android:name="com.lenskart.app.ui.productlist.ProductListingActivity" android:screenOrientation="portrait">
            <intent-filter>
                <action android:name="action_navigate"/>
                <category android:name="android.intent.category.DEFAULT"/>
                <data android:host="@string/deep_link_host" android:path="@string/action_view_product_listing" android:scheme="@string/action_view_scheme"/>
            </intent-filter>
        </activity>
        <activity android:label="@string/title_saved_prescriptions" android:name="com.lenskart.app.ui.prescription.SavedPrescriptionsActivity" android:screenOrientation="portrait">
            <intent-filter>
                <action android:name="action_navigate"/>
                <category android:name="android.intent.category.DEFAULT"/>
                <data android:host="@string/deep_link_host" android:path="@string/action_view_saved_prescription" android:scheme="@string/action_view_scheme"/>
            </intent-filter>
        </activity>
        <activity android:label="@string/title_saved_prescriptions" android:name="com.lenskart.app.ui.prescription.subscription.PrescriptionActivity2" android:screenOrientation="portrait">
            <intent-filter>
                <action android:name="action_navigate"/>
                <category android:name="android.intent.category.DEFAULT"/>
                <data android:host="@string/deep_link_host" android:path="@string/action_view_prescription" android:scheme="@string/action_view_scheme"/>
            </intent-filter>
        </activity>
        <activity android:name="com.lenskart.app.ui.productlist.CategoryActivity" android:screenOrientation="portrait">
            <intent-filter>
                <action android:name="action_navigate"/>
                <category android:name="android.intent.category.DEFAULT"/>
                <data android:host="@string/deep_link_host" android:path="@string/action_view_category" android:scheme="@string/action_view_scheme"/>
            </intent-filter>
        </activity>
        <activity android:label="@string/title_cart" android:name="com.lenskart.app.ui.cart.CartActivity" android:screenOrientation="portrait" android:windowSoftInputMode="adjustNothing">
            <intent-filter>
                <action android:name="action_navigate"/>
                <category android:name="android.intent.category.DEFAULT"/>
                <data android:host="@string/deep_link_host" android:path="@string/action_view_cart" android:scheme="@string/action_view_scheme"/>
            </intent-filter>
        </activity>
        <activity android:label="@string/title_payment" android:name="com.lenskart.app.ui.payment.payu.PayUWebActivity" android:screenOrientation="portrait"/>
        <activity android:label="@string/title_order_details" android:name="com.lenskart.app.ui.order.OrderActivity" android:screenOrientation="portrait">
            <intent-filter>
                <action android:name="action_navigate"/>
                <category android:name="android.intent.category.DEFAULT"/>
                <data android:host="@string/deep_link_host" android:path="@string/action_view_order" android:scheme="@string/action_view_scheme"/>
            </intent-filter>
        </activity>
        <activity android:name="com.lenskart.app.ui.WebViewActivity" android:screenOrientation="portrait">
            <intent-filter>
                <action android:name="action_navigate"/>
                <category android:name="android.intent.category.DEFAULT"/>
                <data android:host="@string/deep_link_host" android:path="@string/action_view_web_view" android:scheme="@string/action_view_scheme"/>
            </intent-filter>
        </activity>
        <activity android:name="com.lenskart.app.ui.ditto.DittoRecordingActivity" android:screenOrientation="portrait">
            <intent-filter>
                <action android:name="action_navigate"/>
                <category android:name="android.intent.category.DEFAULT"/>
                <data android:host="@string/deep_link_host" android:path="@string/action_view_ditto_recording" android:scheme="@string/action_view_scheme"/>
            </intent-filter>
        </activity>
        <activity android:label="@string/title_activity_shortlist" android:name="com.lenskart.app.ui.wishlist.WishlistActivity" android:screenOrientation="portrait"/>
        <activity android:label="@string/title_activity_shortlist" android:name="com.lenskart.app.ui.wishlist.WishlistRecentActivity" android:screenOrientation="portrait">
            <intent-filter>
                <action android:name="action_navigate"/>
                <category android:name="android.intent.category.DEFAULT"/>
                <data android:host="@string/deep_link_host" android:path="@string/action_view_wishlist" android:scheme="@string/action_view_scheme"/>
                <data android:host="@string/deep_link_host" android:path="@string/action_view_recently_viewed" android:scheme="@string/action_view_scheme"/>
            </intent-filter>
        </activity>
        <activity android:name="com.lenskart.app.ui.onboarding.LaunchGuideActivity" android:screenOrientation="portrait">
            <intent-filter>
                <action android:name="action_navigate"/>
                <category android:name="android.intent.category.DEFAULT"/>
                <data android:host="@string/deep_link_host" android:path="@string/action_view_launch_guide" android:scheme="@string/action_view_scheme"/>
            </intent-filter>
        </activity>
        <activity android:name="com.lenskart.app.ui.ditto.recommendation.GetOpinionGuideActivity"/>
        <activity android:name="com.lenskart.baselayer.ui.CrashHandleActivity" android:process=":newprocess" android:screenOrientation="portrait"/>
        <receiver android:enabled="true" android:exported="true" android:name="com.lenskart.app.receivers.AppUpdateReceiver">
            <intent-filter>
                <action android:name="android.intent.action.MY_PACKAGE_REPLACED"/>
            </intent-filter>
        </receiver>
        <meta-data android:name="com.google.android.gms.version" android:value="@integer/google_play_services_version"/>
        <meta-data android:name="com.google.android.geo.API_KEY" android:value="@string/google_maps_api_key"/>
        <meta-data android:name="com.google.android.nearby.messages.API_KEY" android:value="@string/google_maps_api_key"/>
        <activity android:label="@string/title_activity_product_description" android:name="com.lenskart.app.ui.product.ProductDetailPagerActivity" android:screenOrientation="portrait" android:windowSoftInputMode="stateAlwaysHidden">
            <intent-filter>
                <action android:name="action_navigate"/>
                <category android:name="android.intent.category.DEFAULT"/>
                <data android:host="@string/deep_link_host" android:path="@string/action_view_product_detail_pager" android:scheme="@string/action_view_scheme"/>
            </intent-filter>
        </activity>
        <activity android:label="@string/title_contact_us" android:name="com.lenskart.app.ui.ContactUsActivity" android:screenOrientation="portrait">
            <intent-filter>
                <action android:name="action_navigate"/>
                <category android:name="android.intent.category.DEFAULT"/>
                <data android:host="@string/deep_link_host" android:path="@string/action_view_contact_us" android:scheme="@string/action_view_scheme"/>
            </intent-filter>
        </activity>
        <activity android:label="@string/title_about_app" android:name="com.lenskart.app.ui.AboutLenskartActivity" android:screenOrientation="portrait" android:windowSoftInputMode="adjustResize">
            <intent-filter>
                <action android:name="action_navigate"/>
                <category android:name="android.intent.category.DEFAULT"/>
                <data android:host="@string/deep_link_host" android:path="@string/action_view_about_us" android:scheme="@string/action_view_scheme"/>
            </intent-filter>
        </activity>
        <activity android:label="@string/title_offers" android:name="com.lenskart.app.ui.campaigns.CampaignWebActivity" android:screenOrientation="portrait">
            <intent-filter>
                <action android:name="action_navigate"/>
                <category android:name="android.intent.category.DEFAULT"/>
                <data android:host="@string/deep_link_host" android:path="@string/action_view_campaign_web" android:scheme="@string/action_view_scheme"/>
            </intent-filter>
        </activity>
        <activity android:label="Select Address" android:name="com.lenskart.app.ui.address.AddressActivity" android:screenOrientation="portrait" android:windowSoftInputMode="adjustResize|stateHidden">
            <intent-filter>
                <action android:name="action_navigate"/>
                <category android:name="android.intent.category.DEFAULT"/>
                <data android:host="@string/deep_link_host" android:path="@string/action_view_address" android:scheme="@string/action_view_scheme"/>
            </intent-filter>
        </activity>
        <activity android:label="@string/title_make_payment" android:name="com.lenskart.app.ui.checkout.CheckoutActivityNew" android:screenOrientation="portrait"/>
        <activity android:label="Payment" android:name="com.lenskart.app.ui.payment.PaymentWebViewActivity" android:screenOrientation="portrait"/>
        <activity android:label="Enter OTP" android:name="com.lenskart.app.ui.payment.PaymentOTPActivity" android:screenOrientation="portrait" android:windowSoftInputMode="adjustResize|stateHidden"/>
        <activity android:label="Placing Order" android:name="com.lenskart.app.ui.payment.TransactionActivity" android:screenOrientation="portrait" android:windowSoftInputMode="adjustResize|stateHidden"/>
        <activity android:label="Placing Order" android:name="com.lenskart.app.ui.payment2.TransactionActivity" android:screenOrientation="portrait" android:windowSoftInputMode="adjustResize|stateHidden">
            <intent-filter>
                <action android:name="action_navigate"/>
                <category android:name="android.intent.category.DEFAULT"/>
                <data android:host="@string/deep_link_host" android:path="@string/action_view_transaction" android:scheme="@string/action_view_scheme"/>
            </intent-filter>
        </activity>
        <activity android:label="@string/title_store_locator" android:name="com.lenskart.app.ui.storelocator.StoreLocatorActivity" android:screenOrientation="portrait">
            <intent-filter>
                <action android:name="action_navigate"/>
                <category android:name="android.intent.category.DEFAULT"/>
                <data android:host="@string/deep_link_host" android:path="@string/action_view_store_locator" android:scheme="@string/action_view_scheme"/>
            </intent-filter>
        </activity>
        <activity android:label="Choose Delivery Speed" android:name="com.lenskart.app.ui.delivery.DeliveryActivity" android:screenOrientation="portrait">
            <intent-filter>
                <action android:name="action_navigate"/>
                <category android:name="android.intent.category.DEFAULT"/>
                <data android:host="@string/deep_link_host" android:path="@string/action_view_delivery" android:scheme="@string/action_view_scheme"/>
            </intent-filter>
        </activity>
        <activity android:label="Rate Product" android:name="com.lenskart.app.ui.product.ProductRateActivity" android:screenOrientation="portrait" android:windowSoftInputMode="adjustResize|stateHidden">
            <intent-filter>
                <action android:name="action_navigate"/>
                <category android:name="android.intent.category.DEFAULT"/>
                <data android:host="@string/deep_link_host" android:path="@string/action_view_product_rate" android:scheme="@string/action_view_scheme"/>
            </intent-filter>
        </activity>
        <activity android:label="" android:name="com.lenskart.app.ui.ditto.recommendation.OpinionActivity" android:theme="@style/Theme.Lenskart.Light">
            <intent-filter>
                <action android:name="action_navigate"/>
                <category android:name="android.intent.category.DEFAULT"/>
                <data android:host="@string/deep_link_host" android:path="@string/action_view_opinion" android:scheme="@string/action_view_scheme"/>
            </intent-filter>
        </activity>
        <activity android:label="@string/title_visual_search" android:name="com.lenskart.app.ui.visualsearch.VisualSearchActivity" android:screenOrientation="portrait">
            <intent-filter>
                <action android:name="action_navigate"/>
                <category android:name="android.intent.category.DEFAULT"/>
                <data android:host="@string/deep_link_host" android:path="@string/action_view_visual_search" android:scheme="@string/action_view_scheme"/>
            </intent-filter>
        </activity>
        <activity android:name="com.lenskart.app.ui.product.ProductListingGuideActivity" android:screenOrientation="portrait" android:theme="@style/Theme.Lenskart.Light.NoActionBar">
            <intent-filter>
                <action android:name="action_navigate"/>
                <category android:name="android.intent.category.DEFAULT"/>
                <data android:host="@string/deep_link_host" android:path="@string/action_view_product_listing_guide" android:scheme="@string/action_view_scheme"/>
            </intent-filter>
        </activity>
        <receiver android:exported="true" android:name="com.lenskart.app.receivers.CampaignReferrerReceiver">
            <intent-filter>
                <action android:name="com.android.vending.INSTALL_REFERRER"/>
            </intent-filter>
        </receiver>
        <activity android:configChanges="orientation|screenSize" android:name="com.livechatinc.inappchat.ChatWindowActivity" android:screenOrientation="portrait"/>
        <meta-data android:name="io.fabric.ApiKey" android:value="8022bf289bd2e23b12281d8caa0a3967af4ec8f7"/>
        <activity android:name="com.payu.custombrowser.CBActivity" android:screenOrientation="portrait" android:theme="@style/Theme.Lenskart.NoActionBar" android:windowSoftInputMode="stateAlwaysHidden"/>
        <service android:name="com.payu.custombrowser.services.SnoozeService"/>
        <service android:enabled="true" android:exported="false" android:name="com.lenskart.app.service.SuperShareService" android:permission="android.permission.BIND_JOB_SERVICE"/>
        <provider android:authorities="com.lenskart.app.contactsync" android:enabled="true" android:exported="false" android:name="com.lenskart.app.db.ContactsSyncProvider"/>
        <activity android:name="com.lenskart.app.ui.prescription.subscription.SubscriptionActivity" android:screenOrientation="portrait">
            <intent-filter>
                <action android:name="action_navigate"/>
                <category android:name="android.intent.category.DEFAULT"/>
                <data android:host="@string/deep_link_host" android:path="@string/action_view_subscription" android:scheme="@string/action_view_scheme"/>
            </intent-filter>
        </activity>
        <activity android:name="com.lenskart.app.ui.product.lensolution.LensSolutionActivity" android:screenOrientation="portrait"/>
        <activity android:label="@string/title_product_gallery" android:name="com.lenskart.app.ui.product.ProductSecondaryActivity" android:screenOrientation="portrait"/>
        <activity android:label="" android:name="com.lenskart.app.ui.account.AccountActivityNew" android:screenOrientation="portrait">
            <intent-filter>
                <action android:name="action_navigate"/>
                <category android:name="android.intent.category.DEFAULT"/>
                <data android:host="@string/deep_link_host" android:path="@string/action_view_account" android:scheme="@string/action_view_scheme"/>
            </intent-filter>
        </activity>
        <activity android:label="" android:name="com.lenskart.app.ui.athome2.AtHomeActivity" android:screenOrientation="portrait" android:windowSoftInputMode="adjustResize|stateHidden">
            <intent-filter>
                <action android:name="action_navigate"/>
                <category android:name="android.intent.category.DEFAULT"/>
                <data android:host="@string/deep_link_host" android:path="@string/action_view_at_home" android:scheme="@string/action_view_scheme"/>
            </intent-filter>
        </activity>
        <activity android:label="@string/title_filter" android:name="com.lenskart.app.ui.filter.FilterActivity" android:screenOrientation="portrait"/>
        <activity android:label="" android:name="com.lenskart.app.ui.auth.AuthenticationActivity" android:screenOrientation="portrait" android:theme="@style/Theme.Lenskart.Light" android:windowSoftInputMode="adjustResize|stateHidden">
            <intent-filter>
                <action android:name="action_navigate"/>
                <category android:name="android.intent.category.DEFAULT"/>
                <data android:host="@string/deep_link_host" android:path="@string/action_view_authenticate" android:scheme="@string/action_view_scheme"/>
            </intent-filter>
        </activity>
        <activity android:name="com.lenskart.app.ui.ditto.recommendation.DittoRateOthersActivity" android:screenOrientation="portrait" android:theme="@style/Theme.Lenskart.Light">
            <intent-filter>
                <action android:name="action_navigate"/>
                <category android:name="android.intent.category.DEFAULT"/>
                <data android:host="@string/deep_link_host" android:path="@string/action_view_ditto_rate_others" android:scheme="@string/action_view_scheme"/>
            </intent-filter>
        </activity>
        <activity android:name="com.lenskart.app.ui.ditto.recommendation.RateOthersZoomActivty" android:screenOrientation="portrait" android:theme="@style/Theme.Lenskart.Light.DialogActivity"/>
        <activity android:label="@string/title_opinion_result" android:name="com.lenskart.app.ui.ditto.recommendation.GetOpinionResultActivity" android:screenOrientation="portrait"/>
        <activity android:label="@string/title_wallet" android:name="com.lenskart.app.ui.wallet.WalletActivity" android:screenOrientation="portrait">
            <intent-filter>
                <action android:name="action_navigate"/>
                <category android:name="android.intent.category.DEFAULT"/>
                <data android:host="@string/deep_link_host" android:path="@string/action_view_wallet" android:scheme="@string/action_view_scheme"/>
            </intent-filter>
        </activity>
        <activity android:name="com.lenskart.app.ui.referEarn.ReferEarnActivity" android:screenOrientation="portrait">
            <intent-filter>
                <action android:name="action_navigate"/>
                <category android:name="android.intent.category.DEFAULT"/>
                <data android:host="@string/deep_link_host" android:path="@string/action_view_refer_earn" android:scheme="@string/action_view_scheme"/>
            </intent-filter>
        </activity>
        <activity android:label="@string/title_package_list" android:name="com.lenskart.app.ui.product.lensPackage.LensPackageActivity" android:screenOrientation="portrait"/>
        <meta-data android:name="COBROWSE_LICENSE_KEY" android:value="3kA6OQ1aG1PntA"/>
        <meta-data android:name="CLEVERTAP_ACCOUNT_ID" android:value="886-894-RK5Z"/>
        <meta-data android:name="CLEVERTAP_TOKEN" android:value="4cb-6bb"/>
        <service android:name="com.lenskart.app.fcm.MyFirebaseInstanceIDService">
            <intent-filter>
                <action android:name="com.google.firebase.INSTANCE_ID_EVENT"/>
            </intent-filter>
        </service>
        <service android:name="com.lenskart.app.fcm.FcmMessageListenerService">
            <intent-filter>
                <action android:name="com.google.firebase.MESSAGING_EVENT"/>
            </intent-filter>
        </service>
        <service android:exported="false" android:name="com.lenskart.app.fcm.ClearFileStoreJobService">
            <intent-filter>
                <action android:name="com.firebase.jobdispatcher.ACTION_EXECUTE"/>
            </intent-filter>
        </service>
        <service android:exported="false" android:name="com.lenskart.app.service.PersonaService">
            <intent-filter>
                <action android:name="com.firebase.jobdispatcher.ACTION_EXECUTE"/>
            </intent-filter>
        </service>
        <service android:exported="false" android:name="com.lenskart.app.service.FCMChannelJobService">
            <intent-filter>
                <action android:name="com.firebase.jobdispatcher.ACTION_EXECUTE"/>
            </intent-filter>
        </service>
        <activity android:name="com.lenskart.app.ui.MaintenanceModeActivity" android:screenOrientation="portrait" android:theme="@style/Theme.Lenskart.MaintenanceScreenTheme" android:windowSoftInputMode="adjustNothing">
            <intent-filter>
                <action android:name="action_navigate"/>
                <category android:name="android.intent.category.DEFAULT"/>
                <data android:host="@string/deep_link_host" android:path="@string/action_view_maintenance_mode" android:scheme="@string/action_view_scheme"/>
            </intent-filter>
        </activity>
        <activity android:name="com.lenskart.app.ui.productlist.SearchActivity" android:screenOrientation="portrait" android:windowSoftInputMode="adjustResize|stateHidden">
            <intent-filter>
                <action android:name="action_navigate"/>
                <category android:name="android.intent.category.DEFAULT"/>
                <data android:host="@string/deep_link_host" android:path="@string/action_view_search" android:scheme="@string/action_view_scheme"/>
            </intent-filter>
        </activity>
        <activity android:label="@string/label_eye_power" android:name="com.lenskart.app.ui.prescription.SubmitPowerLaterActivity" android:screenOrientation="portrait">
            <intent-filter>
                <action android:name="action_navigate"/>
                <category android:name="android.intent.category.DEFAULT"/>
                <data android:host="@string/deep_link_host" android:path="@string/action_view_submit_power_later" android:scheme="@string/action_view_scheme"/>
            </intent-filter>
        </activity>
        <activity android:name="com.lenskart.app.ui.store.StoreDetailActivity" android:screenOrientation="portrait" android:theme="@style/Theme.Lenskart.Light">
            <intent-filter>
                <action android:name="action_navigate"/>
                <category android:name="android.intent.category.DEFAULT"/>
                <data android:host="@string/deep_link_host" android:path="@string/action_view_store_detail" android:scheme="@string/action_view_scheme"/>
            </intent-filter>
        </activity>
        <activity android:label="" android:name="com.lenskart.app.ui.gold.GoldMembershipSummary" android:screenOrientation="portrait">
            <intent-filter>
                <action android:name="action_navigate"/>
                <category android:name="android.intent.category.DEFAULT"/>
                <data android:host="@string/deep_link_host" android:path="@string/action_view_gold_membership" android:scheme="@string/action_view_scheme"/>
            </intent-filter>
        </activity>
        <activity android:label="" android:name="com.lenskart.app.ui.gold.GoldForStoreActivity" android:screenOrientation="portrait" android:theme="@style/Theme.Lenskart.Light">
            <intent-filter>
                <action android:name="action_navigate"/>
                <category android:name="android.intent.category.DEFAULT"/>
                <data android:host="@string/deep_link_host" android:path="@string/action_view_gold_unlock" android:scheme="@string/action_view_scheme"/>
                <data android:host="@string/deep_link_host" android:path="@string/action_view_gold_unlock_2" android:scheme="@string/action_view_scheme"/>
            </intent-filter>
        </activity>
        <activity android:label="" android:name="com.lenskart.app.ui.product.ReviewGalleryActivity" android:screenOrientation="portrait" android:windowSoftInputMode="adjustNothing"/>
        <activity android:name="com.lenskart.app.ui.reviewRating.MyReviewRatingActivity" android:screenOrientation="portrait" android:windowSoftInputMode="adjustNothing"/>
        <activity android:label="Review Images" android:name="com.lenskart.app.ui.reviewRating.RatingReviewThumbnailActivity" android:screenOrientation="portrait" android:windowSoftInputMode="adjustNothing"/>
        <activity android:name="com.lenskart.app.ui.storelocator.AutoCompleteActivity" android:theme="@style/Theme.Lenskart.TranslucentActivityTheme"/>
        <provider android:authorities=".fileprovider" android:exported="false" android:grantUriPermissions="true" android:name="androidx.core.content.FileProvider">
            <meta-data android:name="android.support.FILE_PROVIDER_PATHS" android:resource="@xml/file_provider_paths"/>
        </provider>
        <activity android:configChanges="keyboardHidden|orientation|screenSize" android:name="com.lenskart.app.ui.athome2.YoutubePlayerActivity" android:screenOrientation="portrait" android:windowSoftInputMode="adjustResize|stateHidden">
            <intent-filter>
                <action android:name="action_navigate"/>
                <category android:name="android.intent.category.DEFAULT"/>
                <data android:host="@string/deep_link_host" android:path="@string/action_view_youtube_player" android:scheme="@string/action_view_scheme"/>
            </intent-filter>
        </activity>
        <activity android:configChanges="keyboardHidden|orientation|screenSize" android:name="com.lenskart.app.ui.onboarding.OnboardingDittoActivity" android:screenOrientation="portrait" android:windowSoftInputMode="adjustResize|stateHidden"/>
        <activity android:configChanges="keyboardHidden|orientation|screenSize" android:label="" android:name="com.lenskart.app.ui.onboarding.OnBoardingActivity" android:screenOrientation="portrait" android:windowSoftInputMode="adjustResize|stateHidden"/>
        <activity android:configChanges="keyboardHidden|orientation|screenSize" android:label="" android:name="com.lenskart.app.ui.onboarding.ChatbotOnboardingActivity" android:screenOrientation="portrait" android:windowSoftInputMode="adjustResize|stateHidden">
            <intent-filter>
                <action android:name="action_navigate"/>
                <category android:name="android.intent.category.DEFAULT"/>
                <data android:host="@string/deep_link_host" android:path="@string/action_view_chat_bot_on_boarding" android:scheme="@string/action_view_scheme"/>
            </intent-filter>
        </activity>
        <service android:exported="false" android:name="com.lenskart.app.service.StoreGeoFenceIntentService" android:permission="android.permission.BIND_JOB_SERVICE"/>
        <service android:exported="false" android:name="com.lenskart.app.service.CityGeoFenceService" android:permission="android.permission.BIND_JOB_SERVICE"/>
        <receiver android:name="com.lenskart.app.receivers.BootCompletedIntentReceiver">
            <intent-filter>
                <action android:name="android.intent.action.BOOT_COMPLETED"/>
            </intent-filter>
        </receiver>
        <receiver android:enabled="true" android:exported="false" android:name="com.lenskart.app.receivers.GeofenceStoreBroadcastReceiver"/>
        <receiver android:enabled="true" android:exported="false" android:name="com.lenskart.app.receivers.GeofenceCityBroadcastReceiver"/>
        <receiver android:exported="false" android:name="com.lenskart.app.receivers.BaseLayerActionReceiver">
            <intent-filter>
                <action android:name="baselayer_action_receiver"/>
            </intent-filter>
        </receiver>
        <activity android:label="@string/title_reviews" android:name="com.lenskart.app.ui.reviewRating.ProductReviewActivity" android:screenOrientation="portrait"/>
        <activity android:name="com.lenskart.app.ui.TextDisplayActivity" android:screenOrientation="portrait">
            <intent-filter>
                <action android:name="action_navigate"/>
                <category android:name="android.intent.category.DEFAULT"/>
                <data android:host="@string/deep_link_host" android:path="@string/action_view_text_display" android:scheme="@string/action_view_scheme"/>
            </intent-filter>
        </activity>
        <activity android:label="Lensa" android:name="com.lenskart.app.chatbot2.ChatBotActivity" android:screenOrientation="portrait" android:theme="@style/Theme.Lenskart">
            <intent-filter>
                <action android:name="action_navigate"/>
                <category android:name="android.intent.category.DEFAULT"/>
                <data android:host="@string/deep_link_host" android:path="@string/action_view_chat" android:scheme="@string/action_view_scheme"/>
            </intent-filter>
        </activity>
        <activity android:label="@string/title_make_payment" android:name="com.lenskart.app.ui.checkout2.CheckoutActivity" android:screenOrientation="portrait">
            <intent-filter>
                <action android:name="action_navigate"/>
                <category android:name="android.intent.category.DEFAULT"/>
                <data android:host="@string/deep_link_host" android:path="@string/action_view_payment" android:scheme="@string/action_view_scheme"/>
            </intent-filter>
        </activity>
        <activity android:label="" android:name="com.lenskart.app.ui.store.AppointmentAtStoreActivity" android:screenOrientation="portrait" android:windowSoftInputMode="adjustResize|stateHidden">
            <intent-filter>
                <action android:name="action_navigate"/>
                <category android:name="android.intent.category.DEFAULT"/>
                <data android:host="@string/deep_link_host" android:path="@string/action_view_appointment_at_store" android:scheme="@string/action_view_scheme"/>
            </intent-filter>
        </activity>
        <activity android:label="@string/label_profile" android:name="com.lenskart.app.ui.account.UserProfileActivity" android:screenOrientation="portrait" android:theme="@style/Theme.Lenskart.Light">
            <intent-filter>
                <action android:name="action_navigate"/>
                <category android:name="android.intent.category.DEFAULT"/>
                <data android:host="@string/deep_link_host" android:path="@string/action_view_user_profile" android:scheme="@string/action_view_scheme"/>
            </intent-filter>
        </activity>
        <activity android:label="@string/title_edit_profile" android:name="com.lenskart.app.ui.account.EditProfileActivity" android:screenOrientation="portrait" android:theme="@style/Theme.Lenskart.Light">
            <intent-filter>
                <action android:name="action_navigate"/>
                <category android:name="android.intent.category.DEFAULT"/>
                <data android:host="@string/deep_link_host" android:path="@string/action_view_edit_user_profile" android:scheme="@string/action_view_scheme"/>
            </intent-filter>
        </activity>
        <activity android:name="com.lenskart.app.ui.onboarding.CameraActivity" android:screenOrientation="portrait" android:theme="@style/Theme.Lenskart.Light">
            <intent-filter>
                <action android:name="action_navigate"/>
                <category android:name="android.intent.category.DEFAULT"/>
                <data android:host="@string/deep_link_host" android:path="@string/action_view_camera_ui" android:scheme="@string/action_view_scheme"/>
            </intent-filter>
        </activity>
        <activity android:name="com.lenskart.app.ui.onboarding.ProfileListActivity" android:screenOrientation="portrait">
            <intent-filter>
                <action android:name="action_navigate"/>
                <category android:name="android.intent.category.DEFAULT"/>
                <data android:host="@string/deep_link_host" android:path="@string/action_view_profile_list" android:scheme="@string/action_view_scheme"/>
            </intent-filter>
        </activity>
        <activity android:name="com.lenskart.app.ui.account.InputNameActivity" android:screenOrientation="portrait">
            <intent-filter>
                <action android:name="action_navigate"/>
                <category android:name="android.intent.category.DEFAULT"/>
                <data android:host="@string/deep_link_host" android:path="@string/action_view_create_profile" android:scheme="@string/action_view_scheme"/>
            </intent-filter>
        </activity>
        <activity android:name="com.lenskart.framesize.ui.FaceAnalysisGuideActivity" android:screenOrientation="portrait">
            <intent-filter>
                <action android:name="action_navigate"/>
                <category android:name="android.intent.category.DEFAULT"/>
                <data android:host="@string/deep_link_host" android:path="@string/action_view_frame_size_guide" android:scheme="@string/action_view_scheme"/>
            </intent-filter>
            <intent-filter>
                <action android:name="action_navigate"/>
                <category android:name="android.intent.category.DEFAULT"/>
                <data android:host="@string/deep_link_host" android:path="@string/action_view_campaign_smile" android:scheme="@string/action_view_scheme"/>
            </intent-filter>
        </activity>
        <activity android:name="com.lenskart.framesize.ui.SmileScoreActivity" android:screenOrientation="portrait"/>
        <activity android:name="com.lenskart.framesize.ui.FrameSizeActivity" android:screenOrientation="portrait">
            <intent-filter>
                <action android:name="action_navigate"/>
                <category android:name="android.intent.category.DEFAULT"/>
                <data android:host="@string/deep_link_host" android:path="@string/action_view_face_analysis" android:scheme="@string/action_view_scheme"/>
            </intent-filter>
        </activity>
        <activity android:name="com.lenskart.framesize.ui.FrameSizeRecommendActivity" android:screenOrientation="portrait" android:theme="@style/Theme.Lenskart.Light">
            <intent-filter>
                <action android:name="action_navigate"/>
                <category android:name="android.intent.category.DEFAULT"/>
                <data android:host="@string/deep_link_host" android:path="@string/action_view_frame_size_result" android:scheme="@string/action_view_scheme"/>
            </intent-filter>
        </activity>
        <activity android:name="com.lenskart.framesize.ui.FaceAnalysisSuccessActivity" android:screenOrientation="portrait">
            <intent-filter>
                <action android:name="action_navigate"/>
                <category android:name="android.intent.category.DEFAULT"/>
                <data android:host="@string/deep_link_host" android:path="@string/action_view_face_analysis_result" android:scheme="@string/action_view_scheme"/>
            </intent-filter>
        </activity>
        <service android:exported="false" android:name="com.lenskart.datalayer.services.CacheJobScheduler">
            <intent-filter>
                <action android:name="com.firebase.jobdispatcher.ACTION_EXECUTE"/>
            </intent-filter>
        </service>
        <service android:exported="false" android:name="com.lenskart.datalayer.services.PrefetchJobService" android:permission="android.permission.BIND_JOB_SERVICE"/>
        <meta-data android:name="com.google.android.gms.vision.DEPENDENCIES" android:value="face"/>
        <activity android:name="com.payu.custombrowser.upiintent.PaymentResponseActivity" android:theme="@style/Theme.Transparent" android:windowSoftInputMode="stateAlwaysHidden"/>
        <activity android:name="com.payu.custombrowser.PreLollipopPaymentsActivity">
            <intent-filter>
                <data android:scheme="com.lenskart.app.success"/>
                <action android:name="android.intent.action.VIEW"/>
                <category android:name="android.intent.category.DEFAULT"/>
                <category android:name="android.intent.category.BROWSABLE"/>
            </intent-filter>
            <intent-filter>
                <data android:scheme="com.lenskart.app.failure"/>
                <action android:name="android.intent.action.VIEW"/>
                <category android:name="android.intent.category.DEFAULT"/>
                <category android:name="android.intent.category.BROWSABLE"/>
            </intent-filter>
        </activity>
        <activity android:name="com.payu.custombrowser.PrePaymentsActivity"/>
        <activity android:exported="false" android:hardwareAccelerated="true" android:label="@string/places_autocomplete_label" android:name="com.google.android.libraries.places.widget.AutocompleteActivity" android:theme="@style/PlacesAutocompleteThemeOverlay" android:windowSoftInputMode="stateAlwaysVisible|adjustPan"/>
        <receiver android:enabled="true" android:exported="false" android:name="com.google.android.gms.analytics.AnalyticsReceiver"/>
        <service android:enabled="true" android:exported="false" android:name="com.google.android.gms.analytics.AnalyticsService"/>
        <service android:enabled="true" android:exported="false" android:name="com.google.android.gms.analytics.AnalyticsJobService" android:permission="android.permission.BIND_JOB_SERVICE"/>
        <activity android:excludeFromRecents="true" android:exported="false" android:name="com.google.android.gms.auth.api.signin.internal.SignInHubActivity" android:theme="@android:style/Theme.Translucent.NoTitleBar"/>
        <service android:exported="true" android:name="com.google.android.gms.auth.api.signin.RevocationBoundService" android:permission="com.google.android.gms.auth.api.signin.permission.REVOCATION_NOTIFICATION"/>
        <provider android:authorities="com.lenskart.app.firebaseperfprovider" android:exported="false" android:initOrder="101" android:name="com.google.firebase.perf.provider.FirebasePerfProvider"/>
        <service android:name="com.google.firebase.components.ComponentDiscoveryService">
            <meta-data android:name="com.google.firebase.components:com.google.firebase.perf.component.FirebasePerfRegistrar" android:value="com.google.firebase.components.ComponentRegistrar"/>
            <meta-data android:name="com.google.firebase.components:com.google.firebase.analytics.connector.internal.AnalyticsConnectorRegistrar" android:value="com.google.firebase.components.ComponentRegistrar"/>
            <meta-data android:name="com.google.firebase.components:com.google.firebase.iid.Registrar" android:value="com.google.firebase.components.ComponentRegistrar"/>
        </service>
        <service android:exported="true" android:name="com.google.firebase.messaging.FirebaseMessagingService">
            <intent-filter android:priority="-500">
                <action android:name="com.google.firebase.MESSAGING_EVENT"/>
            </intent-filter>
        </service>
        <receiver android:enabled="true" android:exported="false" android:name="com.google.android.gms.measurement.AppMeasurementReceiver"/>
        <receiver android:enabled="true" android:exported="true" android:name="com.google.android.gms.measurement.AppMeasurementInstallReferrerReceiver" android:permission="android.permission.INSTALL_PACKAGES">
            <intent-filter>
                <action android:name="com.android.vending.INSTALL_REFERRER"/>
            </intent-filter>
        </receiver>
        <service android:enabled="true" android:exported="false" android:name="com.google.android.gms.measurement.AppMeasurementService"/>
        <service android:enabled="true" android:exported="false" android:name="com.google.android.gms.measurement.AppMeasurementJobService" android:permission="android.permission.BIND_JOB_SERVICE"/>
        <service android:enabled="true" android:exported="false" android:name="com.google.android.gms.tagmanager.TagManagerService"/>
        <activity android:exported="true" android:name="com.google.android.gms.tagmanager.TagManagerPreviewActivity" android:noHistory="true">
            <intent-filter>
                <data android:scheme="tagmanager.c.com.lenskart.app"/>
                <action android:name="android.intent.action.VIEW"/>
                <category android:name="android.intent.category.DEFAULT"/>
                <category android:name="android.intent.category.BROWSABLE"/>
            </intent-filter>
        </activity>
        <receiver android:exported="true" android:name="com.google.firebase.iid.FirebaseInstanceIdReceiver" android:permission="com.google.android.c2dm.permission.SEND">
            <intent-filter>
                <action android:name="com.google.android.c2dm.intent.RECEIVE"/>
                <category android:name="com.lenskart.app"/>
            </intent-filter>
        </receiver>
        <service android:exported="true" android:name="com.google.firebase.iid.FirebaseInstanceIdService">
            <intent-filter android:priority="-500">
                <action android:name="com.google.firebase.INSTANCE_ID_EVENT"/>
            </intent-filter>
        </service>
        <activity android:exported="false" android:name="com.google.android.gms.common.api.GoogleApiActivity" android:theme="@android:style/Theme.Translucent.NoTitleBar"/>
        <provider android:authorities="com.lenskart.app.firebaseinitprovider" android:exported="false" android:initOrder="100" android:name="com.google.firebase.provider.FirebaseInitProvider"/>
        <activity android:configChanges="keyboardHidden" android:name="com.clevertap.android.sdk.InAppNotificationActivity" android:theme="@android:style/Theme.Translucent.NoTitleBar"/>
        <activity android:configChanges="keyboardHidden" android:name="com.clevertap.android.sdk.CTInboxActivity" android:theme="@style/Theme.AppCompat.DayNight.DarkActionBar"/>
        <receiver android:enabled="true" android:exported="false" android:name="com.clevertap.android.sdk.CTPushNotificationReceiver"/>
        <service android:exported="false" android:name="com.clevertap.android.sdk.CTBackgroundIntentService" android:permission="android.permission.BIND_JOB_SERVICE">
            <intent-filter>
                <action android:name="com.clevertap.BG_EVENT"/>
            </intent-filter>
        </service>
        <service android:exported="false" android:name="com.clevertap.android.sdk.CTBackgroundJobService" android:permission="android.permission.BIND_JOB_SERVICE"/>
        <activity android:name="com.payu.magicretry.MainActivity"/>
        <service android:exported="true" android:name="com.firebase.jobdispatcher.GooglePlayReceiver" android:permission="com.google.android.gms.permission.BIND_NETWORK_TASK_SERVICE">
            <intent-filter>
                <action android:name="com.google.android.gms.gcm.ACTION_TASK_READY"/>
            </intent-filter>
        </service>
        <provider android:authorities="com.lenskart.app.lifecycle-process" android:exported="false" android:multiprocess="true" android:name="androidx.lifecycle.ProcessLifecycleOwnerInitializer"/>
        <provider android:authorities="com.lenskart.app.crashlyticsinitprovider" android:exported="false" android:initOrder="90" android:name="com.crashlytics.android.CrashlyticsInitProvider"/>
        <activity android:enabled="false" android:exported="false" android:launchMode="singleInstance" android:name="com.google.android.play.core.missingsplits.PlayCoreMissingSplitsActivity" android:process=":playcore_missing_splits_activity" android:stateNotNeeded="true"/>
        <service android:enabled="true" android:exported="false" android:name="io.cobrowse.CobrowseService"/>
        <service android:exported="true" android:label="@string/cobrowse_service_name" android:name="io.cobrowse.DeviceRegistrationLoop$CobrowseRegistrationJob" android:permission="android.permission.BIND_JOB_SERVICE"/>
        <service android:enabled="@bool/cobrowse_enable_full_device_control" android:exported="false" android:name="io.cobrowse.CobrowseAccessibilityService" android:permission="android.permission.BIND_ACCESSIBILITY_SERVICE">
            <intent-filter>
                <action android:name="android.accessibilityservice.AccessibilityService"/>
                <action android:name="io.cobrowse.REMOTE_CONTROL"/>
            </intent-filter>
            <meta-data android:name="android.accessibilityservice" android:resource="@xml/cobrowse_accessibility_service"/>
        </service>
        <activity android:name="io.cobrowse.ui.CobrowseActivity"/>
        <activity android:label="@string/cobrowse_cobrowse_accessibility_setup_title" android:name="io.cobrowse.ui.CobrowseAccessibilitySetup"/>
        <receiver android:name="io.cobrowse.CobrowseService$Receiver"/>
    </application>
</manifest>